project_BMI_Potato/Calculate_BMI_Potato.py
project_BMI_Potato-0.0.0.4.dist-info/METADATA
project_BMI_Potato-0.0.0.4.dist-info/WHEEL
project_BMI_Potato-0.0.0.4.dist-info/top_level.txt
project_BMI_Potato-0.0.0.4.dist-info/RECORD
