Metadata-Version: 2.1
Name: project-BMI-Potato
Version: 0.0.0.4
Summary: My_BMI_project_start
Home-page: https://github.com/hunterhhunter
Author: Justin jin
Author-email: slugger613@naver.com
License: MIT
Platform: UNKNOWN
Requires-Python: >=3
